malkit/__init__.py
malkit/parallel.py
malkit/py.typed
malkit/typing.py
malkit/utils.py
malkit/data/__init__.py
malkit/data/_dataset.py
malkit/data/_loader.py
malkit/data/binary.py
malkit/features/__init__.py
malkit/features/binary.py
malkit/features/image.py
malkit/torch/__init__.py
malkit/torch/checkpoint.py
malkit/torch/dataset.py
malkit/torch/data/__init__.py
malkit/torch/data/_dataset.py
malkit/torch/data/_loader.py
malkit/torch/data/binary.py
malkit/torch/models/__init__.py
malkit/torch/models/malconv.py
malkit-0.12.0.dist-info/LICENSE
malkit-0.12.0.dist-info/METADATA
malkit-0.12.0.dist-info/WHEEL
malkit-0.12.0.dist-info/top_level.txt
malkit-0.12.0.dist-info/zip-safe
malkit-0.12.0.dist-info/RECORD
