Metadata-Version: 2.1
Name: malkit
Version: 0.12.0
Summary: Malware analysis toolkit for machine learning
Home-page: https://github.com/xymy/malkit
Author: xymy
Author-email: thyfan@163.com
Maintainer: xymy
Maintainer-email: thyfan@163.com
License: MIT
Project-URL: Documentation, https://github.com/xymy/malkit
Project-URL: Issue Tracker, https://github.com/xymy/malkit/issues
Project-URL: Source Code, https://github.com/xymy/malkit
Keywords: malware analysis,machine learning
Classifier: Development Status :: 4 - Beta
Classifier: License :: OSI Approved
Classifier: License :: OSI Approved :: MIT License
Classifier: Operating System :: OS Independent
Classifier: Programming Language :: Python
Classifier: Programming Language :: Python :: 3
Classifier: Programming Language :: Python :: 3 :: Only
Classifier: Programming Language :: Python :: 3.8
Classifier: Programming Language :: Python :: 3.9
Classifier: Programming Language :: Python :: 3.10
Classifier: Programming Language :: Python :: 3.11
Classifier: Topic :: Security
Requires-Python: >=3.8
License-File: LICENSE
Requires-Dist: joblib (>=1.1)
Requires-Dist: numpy (>=1.21)
Requires-Dist: pandas (>=1.3)
Requires-Dist: pillow (>=8.4)
